clite/__init__.py
clite/errors.py
clite/main.py
clite/params_types.py
clite/parser.py
clite/testing.py
clite-0.2.2.dist-info/METADATA
clite-0.2.2.dist-info/WHEEL
clite-0.2.2.dist-info/licenses/LICENSE
clite-0.2.2.dist-info/RECORD
