Metadata-Version: 2.4
Name: clite
Version: 0.2.2
Summary: Small package for creating command line interfaces
Project-URL: Homepage, https://axemanofic.github.io/clite
Project-URL: Documentation, https://axemanofic.github.io/clite
Project-URL: Repository, https://github.com/axemanofic/clite.git
Project-URL: Issues, https://github.com/axemanofic/clite/issues
Project-URL: Changelog, https://github.com/axemanofic/clite/blob/master/CHANGELOG.md
Author-email: Roman Sotnikov <axemanofic@gmail.com>
Maintainer-email: Roman Sotnikov <axemanofic@gmail.com>
License: The MIT License (MIT)
License-File: LICENSE
Keywords: cli,click,python,python3,shell,terminal,typehints,typer,typing
Classifier: Development Status :: 4 - Beta
Classifier: Intended Audience :: Developers
Classifier: Intended Audience :: Information Technology
Classifier: Intended Audience :: System Administrators
Classifier: License :: OSI Approved :: MIT License
Classifier: Operating System :: OS Independent
Classifier: Programming Language :: Python
Classifier: Programming Language :: Python :: 3
Classifier: Programming Language :: Python :: 3 :: Only
Classifier: Programming Language :: Python :: 3.9
Classifier: Programming Language :: Python :: 3.10
Classifier: Programming Language :: Python :: 3.11
Classifier: Programming Language :: Python :: 3.12
Classifier: Programming Language :: Python :: 3.13
Classifier: Topic :: Software Development
Classifier: Topic :: Software Development :: Libraries
Classifier: Topic :: Software Development :: Libraries :: Application Frameworks
Classifier: Topic :: Software Development :: Libraries :: Python Modules
Classifier: Typing :: Typed
Requires-Python: >=3.9
Requires-Dist: typing-extensions>=4.12.2
